Metadata-Version: 2.1
Name: binomial-test
Version: 0.1
Summary: Gaussian distributions
